Metadata-Version: 2.1
Name: sundir
Version: 0.3.1
Summary: Sun Direction Calculator.
Home-page: https://github.com/simgics/sundir
Author: Takayuki Matsuda
Author-email: taka.matsuda@simgics.co.jp
License: UNKNOWN
Platform: UNKNOWN
Classifier: Programming Language :: Python :: 3.7
Classifier: License :: OSI Approved :: Apache Software License
Classifier: Operating System :: OS Independent
Requires-Python: >=3.7
